LICENSE
README.md
setup.py
src/capice.egg-info/PKG-INFO
src/capice.egg-info/SOURCES.txt
src/capice.egg-info/dependency_links.txt
src/capice.egg-info/entry_points.txt
src/capice.egg-info/requires.txt
src/capice.egg-info/top_level.txt
src/molgenis/capice/__init__.py
src/molgenis/capice/capice.py
src/molgenis/capice/main_capice.py
src/molgenis/capice/main_explain.py
src/molgenis/capice/main_predict.py
src/molgenis/capice/main_train.py
src/molgenis/capice/cli/__init__.py
src/molgenis/capice/cli/args_handler_explain.py
src/molgenis/capice/cli/args_handler_parent.py
src/molgenis/capice/cli/args_handler_predict.py
src/molgenis/capice/cli/args_handler_train.py
src/molgenis/capice/core/__init__.py
src/molgenis/capice/core/args_handler.py
src/molgenis/capice/core/capice_exporter.py
src/molgenis/capice/core/capice_manager.py
src/molgenis/capice/core/logger.py
src/molgenis/capice/utilities/__init__.py
src/molgenis/capice/utilities/categorical_processor.py
src/molgenis/capice/utilities/class_suggestor.py
src/molgenis/capice/utilities/column_utils.py
src/molgenis/capice/utilities/custom_logging_filter.py
src/molgenis/capice/utilities/dynamic_loader.py
src/molgenis/capice/utilities/enums.py
src/molgenis/capice/utilities/input_parser.py
src/molgenis/capice/utilities/input_processor.py
src/molgenis/capice/utilities/load_file_postprocessor.py
src/molgenis/capice/utilities/manual_vep_processor.py
src/molgenis/capice/utilities/predictor.py
src/molgenis/capice/validators/__init__.py
src/molgenis/capice/validators/input_validator.py
src/molgenis/capice/validators/model_validator.py
src/molgenis/capice/validators/post_file_parse_validator.py
src/molgenis/capice/validators/post_vep_processing_validator.py
src/molgenis/capice/validators/predict_validator.py
src/molgenis/capice/validators/property_type_validator.py
src/molgenis/capice/validators/version_validator.py
src/molgenis/capice/vep/__init__.py
src/molgenis/capice/vep/amino_acids.py
src/molgenis/capice/vep/cdna_position.py
src/molgenis/capice/vep/cds_position.py
src/molgenis/capice/vep/consequence.py
src/molgenis/capice/vep/length.py
src/molgenis/capice/vep/poly_phen.py
src/molgenis/capice/vep/protein_position.py
