Metadata-Version: 2.1
Name: capice
Version: 5.1.2
Summary: Consequence Agnostic Pathogenicity Interpretation of Clinical Exoma variations. State of the art machine learning to predict SNVs and InDels pathogenicity.
Home-page: https://capice.molgeniscloud.org/
Author: Shuang Li, Robert Sietsma and Molgenis
Author-email: molgenis-support@umcg.nl
License: LGPL-3.0
Classifier: Development Status :: 4 - Beta
Classifier: License :: OSI Approved :: GNU Lesser General Public License v3 (LGPLv3)
Classifier: Programming Language :: Python :: 3.10
Requires-Python: >=3.10
License-File: LICENSE
Requires-Dist: numpy==1.24.1
Requires-Dist: pandas==1.5.3
Requires-Dist: scipy==1.10.0
Requires-Dist: scikit-learn==1.2.1
Requires-Dist: xgboost==1.7.4
Provides-Extra: test
Requires-Dist: pytest; extra == "test"
Requires-Dist: coverage; extra == "test"
Requires-Dist: mypy; extra == "test"
Requires-Dist: flake8; extra == "test"
Requires-Dist: flake8-import-order; extra == "test"
